minikg/__init__.py
minikg/api.py
minikg/build_output.py
minikg/graph_community_detector.py
minikg/graph_edge_compressor.py
minikg/graph_merger.py
minikg/graph_semantic_db.py
minikg/kg_searcher.py
minikg/llm.py
minikg/models.py
minikg/progress_emitter.py
minikg/prompt_context.py
minikg/services.py
minikg/splitter.py
minikg/step_executor.py
minikg/step_executor_test.py
minikg/utils.py
minikg/build_steps/__init__.py
minikg/build_steps/base_step.py
minikg/build_steps/step_apply_edges_to_entities.py
minikg/build_steps/step_cluster_groups.py
minikg/build_steps/step_compress_kg_edges.py
minikg/build_steps/step_define_communities.py
minikg/build_steps/step_extract_chunk_kg.py
minikg/build_steps/step_identify_edges.py
minikg/build_steps/step_identify_entities.py
minikg/build_steps/step_index_community.py
minikg/build_steps/step_merge_kgs.py
minikg/build_steps/step_package.py
minikg/build_steps/step_split_doc.py
minikg/build_steps/step_summarize_community.py
minikg/extractor/__init__.py
minikg/extractor/base_extractor.py
minikg/extractor/entity_extractor.py
minikg/extractor/entity_relationship_extractor.py
minikg/extractor/entity_relationship_extractor_directed.py
minikg/extractor/entity_relationship_extractor_undirected.py
minikg/graphtools/__init__.py
minikg/graphtools/community_detection.py
minikg/graphtools/community_detection_test.py
minikg/graphtools/community_summaries.py
minikg/graphtools/community_summaries_test.py
minikg/graphtools/flatten.py
minikg/graphtools/flatten_test.py
minikg/logic/__init__.py
minikg/logic/communities.py
minikg/logic/communities_test.py
minikg/logic/path.py
minikg/presets/__init__.py
minikg/presets/code.py
minikg/step_coordinators/__init__.py
minikg/step_coordinators/apply_edges_to_entities.py
minikg/step_coordinators/base.py
minikg/step_coordinators/cluster_groups.py
minikg/step_coordinators/compress_redundant_edges.py
minikg/step_coordinators/detect_communities.py
minikg/step_coordinators/extract_chunk_level_kgs.py
minikg-0.4.0.dist-info/METADATA
minikg-0.4.0.dist-info/WHEEL
minikg-0.4.0.dist-info/top_level.txt
minikg-0.4.0.dist-info/RECORD
